{
  "oracleName": "Pagar o Preço",
  "oracleDescription": "Tabela de consequências do Pay the Price",
  "oracleDice": "1d100",
  "oracleEntries": [
    {"entryRange": [1, 2], "entryText": "Piora drasticamente (role novamente e aplique mas pior)", "entryConsequence": null},
    {"entryRange": [3, 5], "entryText": "Uma pessoa ou comunidade confiável perde fé em você ou age contra você", "entryConsequence": null},
    {"entryRange": [6, 9], "entryText": "Uma pessoa ou comunidade que você se importa é exposta a perigo", "entryConsequence": null},
    {"entryRange": [10, 16], "entryText": "Você é separado de algo ou alguém", "entryConsequence": null},
    {"entryRange": [17, 23], "entryText": "Sua ação tem um efeito não intencional", "entryConsequence": null},
    {"entryRange": [24, 32], "entryText": "Algo de valor é perdido ou destruído", "entryConsequence": "resource:supply:-1"},
    {"entryRange": [33, 41], "entryText": "A situação atual piora", "entryConsequence": "resource:momentum:-1"},
    {"entryRange": [42, 50], "entryText": "Um novo perigo ou inimigo é revelado", "entryConsequence": null},
    {"entryRange": [51, 59], "entryText": "Causa atraso ou te coloca em desvantagem", "entryConsequence": "resource:momentum:-1"},
    {"entryRange": [60, 68], "entryText": "É prejudicial", "entryConsequence": "move:Endure Harm"},
    {"entryRange": [69, 77], "entryText": "É estressante", "entryConsequence": "move:Endure Stress"},
    {"entryRange": [78, 85], "entryText": "Desenvolvimento surpreendente complica sua missão", "entryConsequence": null},
    {"entryRange": [86, 90], "entryText": "Desperdiça recursos", "entryConsequence": "resource:supply:-1"},
    {"entryRange": [91, 94], "entryText": "Te força a agir contra suas melhores intenções", "entryConsequence": null},
    {"entryRange": [95, 98], "entryText": "Amigo, companheiro ou aliado em perigo (ou você, se sozinho)", "entryConsequence": "resource:health:-1"},
    {"entryRange": [99, 100], "entryText": "Role duas vezes mais nesta tabela. Ambos ocorrem.", "entryConsequence": null}
  ]
}
